packratt/__init__.py
packratt/application.py
packratt/cache.py
packratt/directories.py
packratt/dispatch.py
packratt/downloads.py
packratt/interface.py
packratt/registry.py
packratt/conf/registry-schema.yaml
packratt/conf/registry.yaml
packratt/tests/__init__.py
packratt/tests/conftest.py
packratt/tests/test_cache.py
packratt/tests/test_get.py
packratt/tests/test_registry.py
packratt-0.1.3.dist-info/LICENSE
packratt-0.1.3.dist-info/METADATA
packratt-0.1.3.dist-info/WHEEL
packratt-0.1.3.dist-info/entry_points.txt
packratt-0.1.3.dist-info/top_level.txt
packratt-0.1.3.dist-info/RECORD
